py1337x/__init__.py
py1337x/config.py
py1337x/models.py
py1337x/parser.py
py1337x/py1337x.py
py1337x/utils.py
py1337x/types/__init__.py
py1337x/types/category.py
py1337x/types/order.py
py1337x/types/sort.py
1337x-2.1.1.dist-info/METADATA
1337x-2.1.1.dist-info/WHEEL
1337x-2.1.1.dist-info/licenses/LICENSE
1337x-2.1.1.dist-info/RECORD
