Metadata-Version: 2.4
Name: 1337x
Version: 2.1.1
Summary: Unofficial API of 1337x.to
Project-URL: Repository, https://github.com/hemantapkh/1337x
Project-URL: Documentation, https://github.com/hemantapkh/1337x/blob/main/README.md
Project-URL: Issue tracker, https://github.com/hemantapkh/1337x/issues
Author-email: Hemanta Pokharel <yo@hemantapkh.com>
License-Expression: MIT
License-File: LICENSE
Keywords: 1337x,torrents
Classifier: Development Status :: 5 - Production/Stable
Classifier: Intended Audience :: Developers
Classifier: License :: OSI Approved :: MIT License
Classifier: Operating System :: OS Independent
Classifier: Topic :: Utilities
Requires-Python: >=3.8
Requires-Dist: asyncer==0.0.11
Requires-Dist: beautifulsoup4<5,>=4.12.3
Requires-Dist: cloudscraper<2,>=1.2.71
Requires-Dist: requests<3,>=2.32.3
